termflow/__init__.py
termflow/__main__.py
termflow/cli.py
termflow/ansi/__init__.py
termflow/ansi/codes.py
termflow/ansi/color.py
termflow/ansi/style.py
termflow/ansi/utils.py
termflow/config/__init__.py
termflow/config/config.py
termflow/core/__init__.py
termflow/core/enums.py
termflow/core/state.py
termflow/parser/__init__.py
termflow/parser/entities.py
termflow/parser/events.py
termflow/parser/inline.py
termflow/parser/parser.py
termflow/render/__init__.py
termflow/render/code.py
termflow/render/heading.py
termflow/render/list.py
termflow/render/renderer.py
termflow/render/style.py
termflow/render/table.py
termflow/render/text.py
termflow/syntax/__init__.py
termflow/syntax/highlighter.py
termflow_md-0.1.9.dist-info/METADATA
termflow_md-0.1.9.dist-info/WHEEL
termflow_md-0.1.9.dist-info/entry_points.txt
termflow_md-0.1.9.dist-info/licenses/LICENSE
termflow_md-0.1.9.dist-info/RECORD
