Metadata-Version: 2.4
Name: termflow-md
Version: 0.1.9
Summary: A streaming markdown renderer for modern terminals
Project-URL: Homepage, https://github.com/mpfaffenberger/termflow
Project-URL: Repository, https://github.com/mpfaffenberger/termflow
Project-URL: Documentation, https://github.com/mpfaffenberger/termflow#readme
Project-URL: Issues, https://github.com/mpfaffenberger/termflow/issues
Author-email: Your Name <your.email@example.com>
License-Expression: MIT
License-File: LICENSE
Keywords: ansi,cli,markdown,renderer,streaming,syntax-highlighting,terminal
Classifier: Development Status :: 3 - Alpha
Classifier: Environment :: Console
Classifier: Intended Audience :: Developers
Classifier: License :: OSI Approved :: MIT License
Classifier: Operating System :: OS Independent
Classifier: Programming Language :: Python :: 3
Classifier: Programming Language :: Python :: 3.11
Classifier: Programming Language :: Python :: 3.12
Classifier: Programming Language :: Python :: 3.13
Classifier: Topic :: Terminals
Classifier: Topic :: Text Processing :: Markup :: Markdown
Classifier: Typing :: Typed
Requires-Python: >=3.11
Requires-Dist: pygments>=2.17.0
Requires-Dist: wcwidth>=0.2.12
Provides-Extra: dev
Requires-Dist: mypy>=1.10.0; extra == 'dev'
Requires-Dist: pytest-cov>=4.1.0; extra == 'dev'
Requires-Dist: pytest>=8.0.0; extra == 'dev'
Requires-Dist: ruff>=0.4.0; extra == 'dev'
Requires-Dist: twine>=6.0.0; extra == 'dev'
